[
    {
      "id": 1,
      "title": "Web Development",
      "description": "Building responsive, user-friendly, and scalable websites tailored to your business needs.",
      "image": "https://source.unsplash.com/featured/?webdevelopment,code",
      "keywords": ["HTML", "CSS", "JavaScript", "React", "Node.js"]
    },
    {
      "id": 2,
      "title": "Mobile App Development",
      "description": "Creating intuitive and performant mobile applications for Android and iOS platforms.",
      "image": "https://source.unsplash.com/featured/?mobile,app",
      "keywords": ["React Native", "Flutter", "API Integration", "UI/UX"]
    },
    {
      "id": 3,
      "title": "UI/UX Design",
      "description": "Designing modern and visually appealing interfaces with a focus on user experience.",
      "image": "https://source.unsplash.com/featured/?design,ui",
      "keywords": ["Wireframes", "Prototyping", "Figma", "Adobe XD"]
    },
    {
      "id": 4,
      "title": "E-commerce Solutions",
      "description": "Developing secure and efficient e-commerce platforms to enhance your online presence.",
      "image": "https://source.unsplash.com/featured/?ecommerce,shopping",
      "keywords": ["Shopify", "WooCommerce", "Payment Integration", "Product Management"]
    },
    {
      "id": 5,
      "title": "SEO Optimization",
      "description": "Improving website ranking on search engines through tailored SEO strategies.",
      "image": "https://source.unsplash.com/featured/?seo,marketing",
      "keywords": ["Keyword Research", "On-Page SEO", "Technical SEO", "Analytics"]
    },
    {
      "id": 6,
      "title": "Backend Development",
      "description": "Building robust server-side solutions to ensure smooth application performance.",
      "image": "https://source.unsplash.com/featured/?backend,server",
      "keywords": ["Node.js", "Express", "MongoDB", "MySQL"]
    }
  ]
  